{
  "schema_version": "v1",
  "symbol": "00728",
  "name": "中国电信",
  "market": "HK",
  "updated_at": "2026-05-30T20:37:34",
  "headline": {
    "title": "中国电信 00728",
    "subtitle": "三轴综合观察",
    "priority": "P2",
    "action": "等待触发",
    "bucket": "watch"
  },
  "overview": {
    "summary": "观察：基本面质量较好；资金面已有覆盖，但尚未形成强确认",
    "bullets": [
      "基本面 71.61/B",
      "60M 技术面 偏多，允许轻仓试错。",
      "资金面 60.5/C"
    ]
  },
  "sections": [
    {
      "key": "fundamental",
      "title": "基本面",
      "rating": "B",
      "score": 71.61,
      "submodel": "digital_infra_v1",
      "report_period": "2025-12-31",
      "summary": "当前综合评级为 B，数字基础设施基本面仍应围绕现金流、分红与云网回报持续跟踪。当前最需要跟踪的是数字基础设施增长兑现偏弱，新业务对利润拉动仍不充分。主要亮点是数字基础设施现金流兑现较好，网络资产经营效率保持稳定。",
      "highlights": [
        "数字基础设施现金流兑现较好，网络资产经营效率保持稳定。",
        "当前 PB 与股息率组合较有吸引力，防御与回报特征兼具。"
      ],
      "risks": [
        "数字基础设施增长兑现偏弱，新业务对利润拉动仍不充分。"
      ],
      "follow_ups": [
        "云网与基础通信业务能否继续兑现成稳定现金流",
        "高股息分配是否仍有经营现金流支撑",
        "数字基础设施投入能否带来可持续回报"
      ],
      "warnings": []
    },
    {
      "key": "technical",
      "title": "技术面",
      "timeframe": "60m",
      "source": "xueqiu",
      "conclusion": "偏多，允许轻仓试错。",
      "suggestion": "分批试仓，跌破 5.16 则严格止损。",
      "overview": [
        "时间区间：2026-01-21 14:00 到 2026-05-29 16:00",
        "K线数量：共 504 根 60M K线",
        "中枢数量：当前识别到 2 个中枢",
        "最新中枢：4.90-4.93，覆盖 02-12 12:00 到 04-29 15:00"
      ],
      "structure": [
        "最新确认向上笔：05-15 15:00 到 05-19 10:30，高点 5.89",
        "未确认向下笔：05-19 10:30 到 05-29 11:30，低点 5.16"
      ],
      "signals": [
        "顶背驰：有",
        "底背驰：无",
        "买点：buy_3",
        "卖点：sell_1"
      ],
      "focus": [
        "观察重点：是否重新站回中枢 4.90-4.93，以及后续一笔是否形成有效突破"
      ]
    },
    {
      "key": "capital_flow",
      "title": "资金面",
      "rating": "C",
      "score": 60.5,
      "source": "eastmoney.southbound_net_buy+eastmoney.southbound_holding.cache",
      "trade_date": "2024-08-26",
      "summary": "资金面存在风险信号，技术面结论需要降低确认度。",
      "strengths": [
        "关键资金指标出现净流入",
        "通道或杠杆资金出现正向变化",
        "未见明显过热信号"
      ],
      "risks": [
        "5日与10日资金持续净流出"
      ],
      "warnings": [
        "资金面部分指标缺失，评分只反映已取得字段"
      ],
      "metrics": [
        {
          "label": "南向净买入",
          "value": "52655048.0"
        },
        {
          "label": "南向持股变化",
          "value": "-775548576.24"
        }
      ]
    }
  ],
  "charts": [
    {
      "timeframe": "60m",
      "path": "stocks/00728/charts/60m.jpg",
      "label": "60M 结构图"
    },
    {
      "timeframe": "15m",
      "path": "stocks/00728/charts/15m.jpg",
      "label": "15M 结构图"
    },
    {
      "timeframe": "day",
      "path": "stocks/00728/charts/day.jpg",
      "label": "DAY 结构图"
    }
  ],
  "disclaimer": "本页面仅用于持仓跟踪与研究，不构成投资建议。"
}
